keynexus/__init__.py
keynexus/client.py
keynexus/exceptions.py
keynexus_python-1.0.1.dist-info/licenses/LICENSE
keynexus_python-1.0.1.dist-info/METADATA
keynexus_python-1.0.1.dist-info/WHEEL
keynexus_python-1.0.1.dist-info/top_level.txt
keynexus_python-1.0.1.dist-info/RECORD
