Metadata-Version: 2.4
Name: keynexus-python
Version: 1.0.1
Summary: Official Python SDK for KeyNexus License Management
Home-page: https://github.com/keynexus/keynexus-python
Author: KeyNexus
Author-email: support@keynexus.es
Project-URL: Bug Reports, https://github.com/keynexus/keynexus-python/issues
Project-URL: Documentation, https://keynexus.es/docs
Project-URL: Source, https://github.com/keynexus/keynexus-python
Keywords: license management authentication licensing drm
Classifier: Development Status :: 4 - Beta
Classifier: Intended Audience :: Developers
Classifier: Topic :: Software Development :: Libraries :: Python Modules
Classifier: License :: OSI Approved :: MIT License
Classifier: Programming Language :: Python :: 3
Classifier: Programming Language :: Python :: 3.7
Classifier: Programming Language :: Python :: 3.8
Classifier: Programming Language :: Python :: 3.9
Classifier: Programming Language :: Python :: 3.10
Classifier: Programming Language :: Python :: 3.11
Requires-Python: >=3.7
License-File: LICENSE
Requires-Dist: requests>=2.25.0
Dynamic: author
Dynamic: author-email
Dynamic: classifier
Dynamic: description
Dynamic: description-content-type
Dynamic: home-page
Dynamic: keywords
Dynamic: license-file
Dynamic: project-url
Dynamic: requires-dist
Dynamic: requires-python
Dynamic: summary
